xrayvisim-0.2.1.dist-info/licenses/LICENSE.rst
xrayvision/__init__.py
xrayvision/_version.py
xrayvision/clean.py
xrayvision/conftest.py
xrayvision/imaging.py
xrayvision/mem.py
xrayvision/transform.py
xrayvision/utils.py
xrayvision/version.py
xrayvision/visibility.py
xrayvision/_dev/__init__.py
xrayvision/_dev/scm_version.py
xrayvision/coordinates/__init__.py
xrayvision/coordinates/frames.py
xrayvision/coordinates/tests/__init__.py
xrayvision/coordinates/tests/test_frames.py
xrayvision/data/README.rst
xrayvision/data/stix_vis.pkl
xrayvision/tests/__init__.py
xrayvision/tests/test_clean.py
xrayvision/tests/test_imaging.py
xrayvision/tests/test_mem.py
xrayvision/tests/test_transform.py
xrayvision/tests/test_visibility.py
xrayvisim-0.2.1.dist-info/METADATA
xrayvisim-0.2.1.dist-info/WHEEL
xrayvisim-0.2.1.dist-info/top_level.txt
xrayvisim-0.2.1.dist-info/RECORD
